rxfoundry/__init__.py
rxfoundry/clients/__init__.py
rxfoundry/clients/p2rx_api/__init__.py
rxfoundry/clients/p2rx_api/api_client.py
rxfoundry/clients/p2rx_api/api_response.py
rxfoundry/clients/p2rx_api/configuration.py
rxfoundry/clients/p2rx_api/exceptions.py
rxfoundry/clients/p2rx_api/py.typed
rxfoundry/clients/p2rx_api/rest.py
rxfoundry/clients/p2rx_api/api/__init__.py
rxfoundry/clients/p2rx_api/api/async_api.py
rxfoundry/clients/p2rx_api/api/code_api.py
rxfoundry/clients/p2rx_api/api/fax_api.py
rxfoundry/clients/p2rx_api/api/medication_api.py
rxfoundry/clients/p2rx_api/api/patient_api.py
rxfoundry/clients/p2rx_api/api/pharmacist_api.py
rxfoundry/clients/p2rx_api/api/pharmacy_api.py
rxfoundry/clients/p2rx_api/api/prescriber_api.py
rxfoundry/clients/p2rx_api/api/prescription_api.py
rxfoundry/clients/p2rx_api/api/token_api.py
rxfoundry/clients/p2rx_api/api/user_api.py
rxfoundry/clients/p2rx_api/api/version_api.py
rxfoundry/clients/p2rx_api/api/virtual_pharmacy_api.py
rxfoundry/clients/p2rx_api/models/__init__.py
rxfoundry/clients/p2rx_api/models/address.py
rxfoundry/clients/p2rx_api/models/asynchronous_response.py
rxfoundry/clients/p2rx_api/models/code.py
rxfoundry/clients/p2rx_api/models/code_qualifier_code.py
rxfoundry/clients/p2rx_api/models/error_message.py
rxfoundry/clients/p2rx_api/models/fax.py
rxfoundry/clients/p2rx_api/models/medication.py
rxfoundry/clients/p2rx_api/models/medication_program_pricing.py
rxfoundry/clients/p2rx_api/models/medication_variant.py
rxfoundry/clients/p2rx_api/models/patient.py
rxfoundry/clients/p2rx_api/models/patient_activity_notification.py
rxfoundry/clients/p2rx_api/models/patient_external_identifier.py
rxfoundry/clients/p2rx_api/models/pharmacist.py
rxfoundry/clients/p2rx_api/models/pharmacy.py
rxfoundry/clients/p2rx_api/models/pharmacy_chain.py
rxfoundry/clients/p2rx_api/models/pharmacy_other_identifier.py
rxfoundry/clients/p2rx_api/models/pharmacy_program_pricing.py
rxfoundry/clients/p2rx_api/models/prescriber.py
rxfoundry_clients_p2rx_api-0.0.603.dist-info/METADATA
rxfoundry_clients_p2rx_api-0.0.603.dist-info/WHEEL
rxfoundry_clients_p2rx_api-0.0.603.dist-info/top_level.txt
rxfoundry_clients_p2rx_api-0.0.603.dist-info/RECORD
